Adafruit_GPIO/MCP230xx.py
Adafruit_GPIO/FT232H.py
Adafruit_GPIO/GPIO.py
Adafruit_GPIO/I2C.py
Adafruit_GPIO/SPI.py
Adafruit_GPIO/PCF8574.py
Adafruit_GPIO/__init__.py
Adafruit_GPIO/Platform.py
Adafruit_GPIO/PWM.py
tests/test_GPIO.py
tests/test_Platform.py
tests/test_SPI.py
tests/__init__.py
tests/test_I2C.py
tests/test_PWM.py
tests/MockGPIO.py
Adafruit_GPIO-1.0.1.dist-info/metadata.json
Adafruit_GPIO-1.0.1.dist-info/METADATA
Adafruit_GPIO-1.0.1.dist-info/RECORD
Adafruit_GPIO-1.0.1.dist-info/WHEEL
Adafruit_GPIO-1.0.1.dist-info/DESCRIPTION.rst
Adafruit_GPIO-1.0.1.dist-info/top_level.txt
